Metadata-Version: 2.4
Name: bpnet
Version: 2.0.0
Summary: BPNet: toolkit to learn motif synthax from high-resolution functional genomics data using convolutional neural networks
Home-page: https://github.com/kundajelab/bpnet
Author: Vivekanandan Ramalingam, Ziga Avsec, Surag Nair, Zahoor Zafrulla
Author-email: vir@stanford.edu
License: MIT license
Keywords: deep learning,computational biology,bioinformatics,genomics
License-File: LICENSE
Requires-Dist: tensorflow==2.4.1
Requires-Dist: tensorflow-probability==0.12.2
Requires-Dist: pysam==0.18.0
Requires-Dist: py2bit==0.3.0
Requires-Dist: tqdm
Requires-Dist: scikit-learn
Requires-Dist: scipy
Requires-Dist: scikit-image
Requires-Dist: scikit-learn
Requires-Dist: deepdish
Requires-Dist: pandas
Requires-Dist: matplotlib
Requires-Dist: plotly
Requires-Dist: deeptools
Requires-Dist: pyfaidx
Requires-Dist: deeplift
Requires-Dist: hdf5plugin
Requires-Dist: kundajelab-shap==1
Provides-Extra: dev
Requires-Dist: pytest; extra == "dev"
Requires-Dist: pytest-cov; extra == "dev"
Dynamic: author
Dynamic: author-email
Dynamic: home-page
Dynamic: keywords
Dynamic: license
Dynamic: license-file
Dynamic: provides-extra
Dynamic: requires-dist
Dynamic: summary
